modelscope_mcp_server/__init__.py
modelscope_mcp_server/__main__.py
modelscope_mcp_server/_version.py
modelscope_mcp_server/cli.py
modelscope_mcp_server/client.py
modelscope_mcp_server/constants.py
modelscope_mcp_server/server.py
modelscope_mcp_server/settings.py
modelscope_mcp_server/types.py
modelscope_mcp_server/tools/__init__.py
modelscope_mcp_server/tools/aigc.py
modelscope_mcp_server/tools/context.py
modelscope_mcp_server/tools/dataset.py
modelscope_mcp_server/tools/mcp.py
modelscope_mcp_server/tools/model.py
modelscope_mcp_server/tools/paper.py
modelscope_mcp_server/tools/studio.py
modelscope_mcp_server/utils/__init__.py
modelscope_mcp_server/utils/metadata.py
modelscope_mcp_server/utils/text.py
modelscope_mcp_server-0.2.1.dist-info/METADATA
modelscope_mcp_server-0.2.1.dist-info/WHEEL
modelscope_mcp_server-0.2.1.dist-info/entry_points.txt
modelscope_mcp_server-0.2.1.dist-info/licenses/LICENSE
modelscope_mcp_server-0.2.1.dist-info/RECORD
