Metadata-Version: 2.4
Name: modelscope-mcp-server
Version: 0.2.1
Summary: A Model Context Protocol (MCP) server that integrates with ModelScope's ecosystem.
Project-URL: Homepage, https://github.com/modelscope/modelscope-mcp-server
Project-URL: Bug Tracker, https://github.com/modelscope/modelscope-mcp-server/issues
Author-email: ModelScope Team <contact@modelscope.cn>
License:                                  Apache License
License-File: LICENSE
Keywords: ai,llm,mcp,model-context-protocol,modelscope
Classifier: Development Status :: 3 - Alpha
Classifier: Intended Audience :: Developers
Classifier: License :: OSI Approved :: Apache Software License
Classifier: Programming Language :: Python :: 3
Classifier: Topic :: Scientific/Engineering :: Artificial Intelligence
Requires-Python: >=3.10
Requires-Dist: fastmcp>=2.10.6
Requires-Dist: httpx[http2]>=0.27.0
Requires-Dist: pydantic-settings>=2.10.1
